<?xml version="1.0" ?>
<!DOCTYPE PubmedArticleSet PUBLIC "-//NLM//DTD PubMedArticle, 1st January 2025//EN" "https://dtd.nlm.nih.gov/ncbi/pubmed/out/pubmed_250101.dtd">
<PubmedArticleSet>
<PubmedArticle><MedlineCitation Status="MEDLINE" Owner="NLM" IndexingMethod="Curated"><PMID Version="1">40983066</PMID><DateCompleted><Year>2025</Year><Month>11</Month><Day>27</Day></DateCompleted><DateRevised><Year>2025</Year><Month>12</Month><Day>19</Day></DateRevised><Article PubModel="Print-Electronic"><Journal><ISSN IssnType="Electronic">2213-2619</ISSN><JournalIssue CitedMedium="Internet"><Volume>13</Volume><Issue>12</Issue><PubDate><Year>2025</Year><Month>Dec</Month></PubDate></JournalIssue><Title>The Lancet. Respiratory medicine</Title><ISOAbbreviation>Lancet Respir Med</ISOAbbreviation></Journal><ArticleTitle>Retifanlimab versus placebo in combination with platinum-based chemotherapy in patients with first-line non-squamous or squamous metastatic non-small-cell lung cancer (POD1UM-304): a phase 3, multiregional, placebo-controlled, double-blind, randomised study.</ArticleTitle><Pagination><StartPage>1096</StartPage><EndPage>1107</EndPage><MedlinePgn>1096-1107</MedlinePgn></Pagination><ELocationID EIdType="doi" ValidYN="Y">10.1016/S2213-2600(25)00209-7</ELocationID><ELocationID EIdType="pii" ValidYN="Y">S2213-2600(25)00209-7</ELocationID><Abstract><AbstractText Label="BACKGROUND" NlmCategory="BACKGROUND">Checkpoint inhibitors, including combinations with standard-of-care chemotherapy, have shown survival benefit in patients with metastatic non-small-cell lung cancer (NSCLC); however, access to these drugs varies. We aimed to evaluate the efficacy of the PD-1 inhibitor retifanlimab plus platinum-based chemotherapy as first-line treatment for non-squamous or squamous metastatic NSCLC.</AbstractText><AbstractText Label="METHODS" NlmCategory="METHODS">POD1UM-304 was a phase 3, multiregional, placebo-controlled, double-blind, randomised study conducted in approximately 124 hospitals and private clinical centres in 16 countries. Male and female adults aged 18 years or older with squamous or non-squamous stage IV NSCLC (staging by American Joint Committee on Cancer version 8) with Eastern Cooperative Oncology Group performance status 0 or 1 and no previous systemic therapy for metastatic NSCLC were eligible. Patients were randomly assigned (2:1) using interactive response technology to receive intravenous retifanlimab 375 mg or matching placebo on day 1 of each 21-day cycle plus standard platinum-based chemotherapy according to tumour histology for up to 2 years. Patients with non-squamous NSCLC received pemetrexed 500 mg/m<sup>2</sup> plus cisplatin 75 mg/m<sup>2</sup> on day 1 for four cycles, or carboplatin area under the curve (AUC) 5 on day 1 for four cycles, followed by pemetrexed 500 mg/m<sup>2</sup> on day 1 of each subsequent 21-day cycle, all administered intravenously, until disease progression or unacceptable toxicity. Patients with squamous NSCLC received intravenous carboplatin AUC 6 plus intravenous paclitaxel 200 mg/m<sup>2</sup> on day 1 for four cycles or intravenous nab-paclitaxel 100 mg/m<sup>2</sup> on days 1, 8, and 15 for four cycles. Treatment with retifanlimab or placebo was given for up to 35 cycles, unless there was disease progression, unacceptable toxicity, or withdrawal of consent. Randomisation was stratified by PD-L1 expression tumour proportion score, geographical region, and predominant tumour histology. The primary endpoint was overall survival, defined as time from randomisation until death due to any cause, analysed in the full analysis set. Safety was evaluated in all randomly assigned patients who received at least one dose of study drug. This trial is registered with ClinicalTrials.gov (NCT04205812) and is active but no longer enrolling.</AbstractText><AbstractText Label="FINDINGS" NlmCategory="RESULTS">Between Sept 11, 2020, and March 14, 2023, 1388 patients were assessed for eligibility, 583 of whom were randomly assigned to retifanlimab plus chemotherapy (n=391) or placebo plus chemotherapy (n=192). 381 (65%) patients had non-squamous NSCLC and 202 (35%) had squamous NSCLC; 467 (80%) patients were male and 116 (20%) were female. Median age was 64 years (IQR 58-68). Median overall survival was longer in the retifanlimab plus chemotherapy group than in the placebo plus chemotherapy group (18&#xb7;1 months [95% CI 16&#xb7;2-21&#xb7;0] vs 13&#xb7;4 months [11&#xb7;0-16&#xb7;7]; hazard ratio 0&#xb7;75 [95% CI 0&#xb7;60-0&#xb7;93]; p=0&#xb7;0042). Overall, higher incidences of treatment-emergent adverse events that were serious (158 [41%] of 389 vs 57 [30%] of 190), grade 3 or worse (238 [61%] vs 103 [54%]), or led to retifanlimab or placebo dose delay (169 [43%] vs 67 [35%]) or discontinuation (33 [8%] vs nine [5%]) were observed in the retifanlimab plus chemotherapy group than in the placebo plus chemotherapy group. The proportions of fatal COVID-19-related treatment-emergent adverse events were similar in the retifanlimab plus chemotherapy group and the placebo plus chemotherapy group (four [1%] vs five [3%]).</AbstractText><AbstractText Label="INTERPRETATION" NlmCategory="CONCLUSIONS">Retifanlimab improved overall survival compared with placebo when added to platinum-based chemotherapy, with a safety profile that is representative of previous PD-1 and PD-L1 inhibitor-chemotherapy combinations. Adding retifanlimab to first-line chemotherapy could be a potential treatment option for patients with squamous or non-squamous metastatic NSCLC.</AbstractText><AbstractText Label="FUNDING" NlmCategory="BACKGROUND">Incyte.</AbstractText><CopyrightInformation>&#xa9; 2025 Elsevier Ltd. All rights reserved, including those for text and data mining, AI training, and similar technologies.</CopyrightInformation></Abstract><AuthorList CompleteYN="Y"><Author ValidYN="Y"><LastName>Lu</LastName><ForeName>Shun</ForeName><Initials>S</Initials><AffiliationInfo><Affiliation>Shanghai Chest Hospital, School of Medicine, Shanghai Jiao Tong University, Shanghai, China. Electronic address: shunlu@sjtu.edu.cn.</Affiliation></AffiliationInfo></Author><Author ValidYN="Y"><LastName>Vynnychenko</LastName><ForeName>Oleksandr</ForeName><Initials>O</Initials><AffiliationInfo><Affiliation>University Hospital of Sumy State University, Sumy, Ukraine.</Affiliation></AffiliationInfo></Author><Author ValidYN="Y"><LastName>Kulyaba</LastName><ForeName>Yaroslav</ForeName><Initials>Y</Initials><AffiliationInfo><Affiliation>Medical Center Asklepion, Kyiv, Ukraine.</Affiliation></AffiliationInfo></Author><Author ValidYN="Y"><LastName>Kuchava</LastName><ForeName>Vladimer</ForeName><Initials>V</Initials><AffiliationInfo><Affiliation>Institute of Clinical Oncology, Tbilisi, Georgia.</Affiliation></AffiliationInfo></Author><Author ValidYN="Y"><LastName>Ibrahim</LastName><ForeName>Aishah</ForeName><Initials>A</Initials><AffiliationInfo><Affiliation>Hospital Tengku Ampuan Afzan, Kuantan, Malaysia.</Affiliation></AffiliationInfo></Author><Author ValidYN="Y"><LastName>Moiseenko</LastName><ForeName>Fedor</ForeName><Initials>F</Initials><AffiliationInfo><Affiliation>FSBI CRPC for Specialized Medical Care Oncology, Saint Petersburg, Russia.</Affiliation></AffiliationInfo></Author><Author ValidYN="Y"><LastName>Arslan</LastName><ForeName>Cagatay</ForeName><Initials>C</Initials><AffiliationInfo><Affiliation>Izmir Economy University Medical Point Hospital, Izmir, T&#xfc;rkiye.</Affiliation></AffiliationInfo></Author><Author ValidYN="Y"><LastName>Nguyen</LastName><ForeName>Duong Thanh</ForeName><Initials>DT</Initials><AffiliationInfo><Affiliation>National Lung Hospital, Hanoi, Viet Nam.</Affiliation></AffiliationInfo></Author><Author ValidYN="Y"><LastName>Petrovic</LastName><ForeName>Marina</ForeName><Initials>M</Initials><AffiliationInfo><Affiliation>University Clinical Centre Kragujevac and Faculty of Medical Sciences, Department of Internal Medicine, University of Kragujevac, Kragujevac, Serbia.</Affiliation></AffiliationInfo></Author><Author ValidYN="Y"><LastName>Cicin</LastName><ForeName>Irfan</ForeName><Initials>I</Initials><AffiliationInfo><Affiliation>Istinye University Medical Oncology, Istanbul, T&#xfc;rkiye; Istanbul Aiden University, VM Medical Park Florya Hospital, Istanbul, T&#xfc;rkiye.</Affiliation></AffiliationInfo></Author><Author ValidYN="Y"><LastName>Bibichadze</LastName><ForeName>Khatuna</ForeName><Initials>K</Initials><AffiliationInfo><Affiliation>JSC EVEX Hospitals, Kutaisi, Georgia.</Affiliation></AffiliationInfo></Author><Author ValidYN="Y"><LastName>Cil</LastName><ForeName>Timucin</ForeName><Initials>T</Initials><AffiliationInfo><Affiliation>University of Health Science, Adana City Education and Research Hospital, Adana, T&#xfc;rkiye.</Affiliation></AffiliationInfo></Author><Author ValidYN="Y"><LastName>Shi</LastName><ForeName>Jianhua</ForeName><Initials>J</Initials><AffiliationInfo><Affiliation>Linyi Cancer Hospital, Shandong, China.</Affiliation></AffiliationInfo></Author><Author ValidYN="Y"><LastName>Olmez</LastName><ForeName>Omer Fatih</ForeName><Initials>OF</Initials><AffiliationInfo><Affiliation>Department of Medical Oncology, Medipol University Faculty of Medicine, Istanbul, T&#xfc;rkiye.</Affiliation></AffiliationInfo></Author><Author ValidYN="Y"><LastName>Gogishvili</LastName><ForeName>Miranda</ForeName><Initials>M</Initials><AffiliationInfo><Affiliation>High Technology Medical Center, Tbilisi, Georgia.</Affiliation></AffiliationInfo></Author><Author ValidYN="Y"><LastName>Artac</LastName><ForeName>Mehmet</ForeName><Initials>M</Initials><AffiliationInfo><Affiliation>Necmettin Erbakan University, Konya, T&#xfc;rkiye.</Affiliation></AffiliationInfo></Author><Author ValidYN="Y"><LastName>Nguyen</LastName><ForeName>Hoang Gia</ForeName><Initials>HG</Initials><AffiliationInfo><Affiliation>Hanoi Oncology Hospital, Hanoi, Viet Nam.</Affiliation></AffiliationInfo></Author><Author ValidYN="Y"><LastName>Cornfeld</LastName><ForeName>Mark</ForeName><Initials>M</Initials><AffiliationInfo><Affiliation>Incyte Corporation, Wilmington, DE, USA.</Affiliation></AffiliationInfo></Author><Author ValidYN="Y"><LastName>Tian</LastName><ForeName>Chuan</ForeName><Initials>C</Initials><AffiliationInfo><Affiliation>Incyte Corporation, Wilmington, DE, USA.</Affiliation></AffiliationInfo></Author><Author ValidYN="Y"><LastName>Munteanu</LastName><ForeName>Mihaela C</ForeName><Initials>MC</Initials><AffiliationInfo><Affiliation>Incyte Corporation, Wilmington, DE, USA.</Affiliation></AffiliationInfo></Author><Author ValidYN="Y"><LastName>Sette</LastName><ForeName>Claudia V M</ForeName><Initials>CVM</Initials><AffiliationInfo><Affiliation>Centro de Estudos e Pesquisas de Hematologia e Oncologia, Santo Andr&#xe9;, S&#xe3;o Paulo, Brazil.</Affiliation></AffiliationInfo></Author><Author ValidYN="Y"><LastName>Bondarenko</LastName><ForeName>Igor</ForeName><Initials>I</Initials><AffiliationInfo><Affiliation>Oncology and Medical Radiology Department, Dnipropetrovsk State Medical Academy, Dnipro, Ukraine.</Affiliation></AffiliationInfo></Author><Author ValidYN="Y"><CollectiveName>POD1UM-304 Study Team</CollectiveName></Author></AuthorList><Language>eng</Language><DataBankList CompleteYN="Y"><DataBank><DataBankName>ClinicalTrials.gov</DataBankName><AccessionNumberList><AccessionNumber>NCT04205812</AccessionNumber></AccessionNumberList></DataBank></DataBankList><PublicationTypeList><PublicationType UI="D016428">Journal Article</PublicationType><PublicationType UI="D016449">Randomized Controlled Trial</PublicationType><PublicationType UI="D017428">Clinical Trial, Phase III</PublicationType><PublicationType UI="D016448">Multicenter Study</PublicationType></PublicationTypeList><ArticleDate DateType="Electronic"><Year>2025</Year><Month>09</Month><Day>19</Day></ArticleDate></Article><MedlineJournalInfo><Country>England</Country><MedlineTA>Lancet Respir Med</MedlineTA><NlmUniqueID>101605555</NlmUniqueID><ISSNLinking>2213-2600</ISSNLinking></MedlineJournalInfo><ChemicalList><Chemical><RegistryNumber>P88XT4IS4D</RegistryNumber><NameOfSubstance UI="D017239">Paclitaxel</NameOfSubstance></Chemical><Chemical><RegistryNumber>BG3F62OND5</RegistryNumber><NameOfSubstance UI="D016190">Carboplatin</NameOfSubstance></Chemical><Chemical><RegistryNumber>Q20Q21Q62J</RegistryNumber><NameOfSubstance UI="D002945">Cisplatin</NameOfSubstance></Chemical></ChemicalList><CitationSubset>IM</CitationSubset><MeshHeadingList><MeshHeading><DescriptorName UI="D006801" MajorTopicYN="N">Humans</DescriptorName></MeshHeading><MeshHeading><DescriptorName UI="D002289" MajorTopicYN="Y">Carcinoma, Non-Small-Cell Lung</DescriptorName><QualifierName UI="Q000188" MajorTopicYN="N">drug therapy</QualifierName><QualifierName UI="Q000473" MajorTopicYN="N">pathology</QualifierName></MeshHeading><MeshHeading><DescriptorName UI="D008297" MajorTopicYN="N">Male</DescriptorName></MeshHeading><MeshHeading><DescriptorName UI="D005260" MajorTopicYN="N">Female</DescriptorName></MeshHeading><MeshHeading><DescriptorName UI="D008175" MajorTopicYN="Y">Lung Neoplasms</DescriptorName><QualifierName UI="Q000188" MajorTopicYN="N">drug therapy</QualifierName><QualifierName UI="Q000473" MajorTopicYN="N">pathology</QualifierName><QualifierName UI="Q000401" MajorTopicYN="N">mortality</QualifierName></MeshHeading><MeshHeading><DescriptorName UI="D008875" MajorTopicYN="N">Middle Aged</DescriptorName></MeshHeading><MeshHeading><DescriptorName UI="D004311" MajorTopicYN="N">Double-Blind Method</DescriptorName></MeshHeading><MeshHeading><DescriptorName UI="D000368" MajorTopicYN="N">Aged</DescriptorName></MeshHeading><MeshHeading><DescriptorName UI="D000971" MajorTopicYN="Y">Antineoplastic Combined Chemotherapy Protocols</DescriptorName><QualifierName UI="Q000627" MajorTopicYN="N">therapeutic use</QualifierName><QualifierName UI="Q000008" MajorTopicYN="N">administration &amp; dosage</QualifierName></MeshHeading><MeshHeading><DescriptorName UI="D017239" MajorTopicYN="N">Paclitaxel</DescriptorName><QualifierName UI="Q000008" MajorTopicYN="N">administration &amp; dosage</QualifierName></MeshHeading><MeshHeading><DescriptorName UI="D016190" MajorTopicYN="N">Carboplatin</DescriptorName><QualifierName UI="Q000008" MajorTopicYN="N">administration &amp; dosage</QualifierName></MeshHeading><MeshHeading><DescriptorName UI="D002945" MajorTopicYN="N">Cisplatin</DescriptorName><QualifierName UI="Q000008" MajorTopicYN="N">administration &amp; dosage</QualifierName></MeshHeading><MeshHeading><DescriptorName UI="D000328" MajorTopicYN="N">Adult</DescriptorName></MeshHeading></MeshHeadingList><CoiStatement>Declaration of interests SL reports research support from AstraZeneca, BeiGene, Hansoh Pharmaceuticals, Jiangsu Hengrui Pharmaceuticals, Hutchison MediPharma, and Roche; speaker fees from AstraZeneca, Hansoh Pharmaceuticals, Jiangsu Hengrui Pharmaceuticals, and Roche; participating in advisory boards/consultancy work for AstraZeneca, Boehringer Ingelheim, GenomiCare, Hutchison MediPharma, InventisBio, Menarini, Pfizer, Roche, Yuhan Corporation, and Zai Lab; participating in advisory boards for Phanes Therapeutics, Shanghai Fosun Pharmaceutical, and Simcere Zaiming Pharmaceutical; and being a director/board member for Innovent Bio. AI reports receiving honoraria/participating in speakers bureaus for AstraZeneca, Boehringer Ingelheim, GSK, Menarini, Mundipharma, Novartis, and Orient Europharma; and participating in clinical advisory boards for Boehringer Ingelheim and Novartis. FM reports honoraria from AstraZeneca, BIOCAD, Boehringer Ingelheim, Bristol Myers Squibb, Lilly, Merck, MSD, Novartis, Pfizer, Roche, Sanofi, and Takeda; consulting or advisory roles for AstraZeneca, Boehringer Ingelheim, and Novartis; participating in speakers bureaus for AstraZeneca, Boehringer Ingelheim, Bristol Myers Squibb, Lilly, Roche, and Takeda; research funding from BIOCAD; travel, accommodation, and expenses from Boehringer Ingelheim, Pfizer, Sanofi, and Takeda; and other relationship (educational activities) for AstraZeneca, Bristol Myers Squibb, MSD, Pfizer, and Roche. CA reports consulting or advisory roles for Amgen, Astellas, AstraZeneca, Bayer, Johnson &amp; Johnson, Lilly, Pfizer, and Teva; and research funding from Amgen, Astellas, AstraZeneca, Bayer, Bristol Myers Squibb, Daiichi Sankyo, Henlius, Johnson &amp; Johnson, Lilly, MSD, Nektar Therapeutics, Novartis, Pfizer, Roche, Sanofi-Aventis, Teva Pharmaceuticals, and Yuhan Corporation. IC reports consulting or advisory roles (institutional) for AbbVie, Abdi Ibrahim Pharmaceuticals, Bristol Myers Squibb, Janssen Oncology, Lilly, MSD Oncology, Nobelpharma, Novartis/Ipsen, Pfizer, Roche, Servier, and Teva Pharmaceuticals; and participating in speakers bureaus (institutional) for Abdi Ibrahim, Bristol Myers Squibb, Novartis, Pfizer, and Roche. TC reports advisory roles (institutional) for AstraZeneca; and research funding from AbbVie, Amgen, Arcus Biosciences/Gilead, AstraZeneca, Bayer, BioNTech, Bristol Myers Squibb, Daiichi Sankyo, Incyte Corporation, Janssen, Lilly, Merck KGaA, MSD, Novartis, Pfizer, Regeneron Pharmaceuticals, Roche, Samsung Bioepis, Sichuan Kelun-Biotech Biopharmaceutical, and Stemline Therapeutics. OFO reports research funding from Daiichi Sankyo, Menarini Silicon Biosystems, Merck KGaA, MSD, Novartis, Roche, and Tempus; and participating in advisory boards for Abdi Ibrahim, AstraZeneca, Bristol Myers Squibb, Daiichi Sankyo, Janssen Oncology, Lilly, Menarini Silicon Biosystems, Nobelpharma, Novartis, Pfizer, and Roche. MA reports honoraria from Amgen, Astellas, AstraZeneca, Bayer, Bristol Myers Squibb, MSD, Novartis, Pfizer, and Roche. MC, CT, and MCM report employment and stock ownership from Incyte. CVMS reports participating in advisory boards for AstraZeneca and Janssen Oncology; being a speaker for AstraZeneca, Daiichi Sankyo, Janssen Oncology, Lilly, Merck, MSD Oncology, and Pfizer; and travel expenses from Boehringer Ingelheim, Daiichi Sankyo, and Janssen Oncology. All other authors declare no competing interests.</CoiStatement></MedlineCitation><PubmedData><History><PubMedPubDate PubStatus="received"><Year>2024</Year><Month>11</Month><Day>25</Day></PubMedPubDate><PubMedPubDate PubStatus="revised"><Year>2025</Year><Month>5</Month><Day>16</Day></PubMedPubDate><PubMedPubDate PubStatus="accepted"><Year>2025</Year><Month>6</Month><Day>5</Day></PubMedPubDate><PubMedPubDate PubStatus="medline"><Year>2025</Year><Month>11</Month><Day>28</Day><Hour>0</Hour><Minute>26</Minute></PubMedPubDate><PubMedPubDate PubStatus="pubmed"><Year>2025</Year><Month>9</Month><Day>23</Day><Hour>3</Hour><Minute>17</Minute></PubMedPubDate><PubMedPubDate PubStatus="entrez"><Year>2025</Year><Month>9</Month><Day>22</Day><Hour>18</Hour><Minute>52</Minute></PubMedPubDate></History><PublicationStatus>ppublish</PublicationStatus><ArticleIdList><ArticleId IdType="pubmed">40983066</ArticleId><ArticleId IdType="doi">10.1016/S2213-2600(25)00209-7</ArticleId><ArticleId IdType="pii">S2213-2600(25)00209-7</ArticleId></ArticleIdList></PubmedData></PubmedArticle></PubmedArticleSet>